{
  "subtitle": "", 
  "description": "Umubyeyi wonsa, kabone n\u2019iyo yaba ate ikibazo cy\u2019imirire mibi, shobora guko-meza konsa umwana we, yemwe no mu bihe hari icyorezo.", 
  "language": "kin_RW", 
  "title": "Umubyeyi wonsa, kabone n\u2019iyo yaba ate ikibazo cy\u2019imirire mibi, shobora guko-meza konsa umwana we, yemwe no mu bihe hari icyorezo.", 
  "primary_category": "3c09cebe82174a50a52571a498767451", 
  "created_at": "2015-03-02T15:22:15.303585+00:00", 
  "featured_in_category": false, 
  "modified_at": "2015-03-02T15:22:15.303817+00:00", 
  "_version": {
    "package_version": "1.0.0", 
    "language_version": "2.7.6", 
    "language": "python", 
    "language_version_string": "2.7.6 (default, Mar 22 2014, 23:03:41) \n[GCC 4.8.2]", 
    "package": "elastic-git"
  }, 
  "linked_pages": [], 
  "id": null, 
  "content": "Umubyeyi wonsa, kabone n\u2019iyo yaba ate ikibazo cy\u2019imirire mibi, shobora guko-meza konsa umwana we, yemwe no mu bihe hari icyorezo.", 
  "source": null, 
  "featured": false, 
  "author_tags": [], 
  "image": null, 
  "published": null, 
  "position": 0, 
  "image_host": "http://thumbor.unicore.io", 
  "slug": "umubyeyi-wonsa-kabone-niyo-yaba-ate-ikibazo-cyimirire-mibi-shobora-guko-meza-konsa-umwana-we-yemwe-no-mu-bihe-hari-icyorezo", 
  "uuid": "7a5fbfa8567842b5b63182db2852ed7d"
}