{
  "subtitle": "", 
  "uuid": "167b9dcc90c44d3d829d86cd11285743", 
  "language": "kin_RW", 
  "title": "VIRUSI ITERA SIDA(HIV) NA SIDA", 
  "image": null, 
  "_version": {
    "package_version": "0.3.7", 
    "language_version": "2.7.6", 
    "language": "python", 
    "language_version_string": "2.7.6 (default, Mar 22 2014, 23:03:41) \n[GCC 4.8.2]", 
    "package": "elastic-git"
  }, 
  "slug": "virusi-itera-sidahiv-na-sida", 
  "source": null, 
  "position": 3, 
  "image_host": "http://thumbor.unicore.io", 
  "featured_in_navbar": false, 
  "id": null
}